sqlalchemy_json_querybuilder/__init__.py
sqlalchemy_json_querybuilder/commons/__init__.py
sqlalchemy_json_querybuilder/commons/callable.py
sqlalchemy_json_querybuilder/commons/commons.py
sqlalchemy_json_querybuilder/commons/lazydict.py
sqlalchemy_json_querybuilder/commons/error_handlers/__init__.py
sqlalchemy_json_querybuilder/commons/error_handlers/errors/__init__.py
sqlalchemy_json_querybuilder/commons/error_handlers/errors/errors.py
sqlalchemy_json_querybuilder/commons/error_handlers/exceptions/__init__.py
sqlalchemy_json_querybuilder/commons/error_handlers/exceptions/exceptions.py
sqlalchemy_json_querybuilder/constants/__init__.py
sqlalchemy_json_querybuilder/constants/error_codes.py
sqlalchemy_json_querybuilder/querybuilder/__init__.py
sqlalchemy_json_querybuilder/querybuilder/criterion.py
sqlalchemy_json_querybuilder/querybuilder/operators.py
sqlalchemy_json_querybuilder/querybuilder/search.py
sqlalchemy_json_querybuilder-1.2.3.dist-info/METADATA
sqlalchemy_json_querybuilder-1.2.3.dist-info/RECORD
sqlalchemy_json_querybuilder-1.2.3.dist-info/WHEEL
sqlalchemy_json_querybuilder-1.2.3.dist-info/top_level.txt
