Metadata-Version: 2.1
Name: sqlalchemy_json_querybuilder
Version: 1.2.3
Summary: Querybuilder to use SqlAlchemy ORM by feeding JSON/object as input
Home-page: https://github.com/suyash248/sqlalchemy-json-querybuilder
Author: Suyash Soni
Author-email: suyash.soni248@gmail.com
Maintainer: Suyash Soni
License: UNKNOWN
Platform: UNKNOWN
Classifier: Operating System :: OS Independent
Classifier: Intended Audience :: Developers
Classifier: License :: OSI Approved :: MIT License
Classifier: Programming Language :: Python :: 3
Requires-Python: >=3
